chippermillet/__init__.py
chippermillet/core.py
chippermillet-0.0.1.dist-info/LICENSE
chippermillet-0.0.1.dist-info/METADATA
chippermillet-0.0.1.dist-info/WHEEL
chippermillet-0.0.1.dist-info/top_level.txt
chippermillet-0.0.1.dist-info/RECORD
