Metadata-Version: 2.1
Name: chippermillet
Version: 0.0.1
Summary: Cryptography from madhava
Home-page: https://github.com/Madhava-mng/chipperMillet
Author: Madhava-mng
Author-email: alformint@gmail.com
License: UNKNOWN
Platform: UNKNOWN
Classifier: Programming Language :: Python :: 3
Classifier: License :: OSI Approved :: MIT License
Classifier: Operating System :: OS Independent
Requires-Python: >=3.6
